{
  "_format": "hh-sol-cache-2",
  "files": {
    "C:\\Users\\admin\\Desktop\\voteDapp\\contracts\\VoteDapp.sol": {
      "lastModificationDate": 1713180398005,
      "contentHash": "9793e37859ab5159f86168e8bbcce851",
      "sourceName": "contracts/VoteDapp.sol",
      "solcConfig": {
        "version": "0.8.24",
        "settings": {
          "evmVersion": "paris",
          "optimizer": {
            "enabled": false,
            "runs": 200
          },
          "outputSelection": {
            "*": {
              "*": [
                "abi",
                "evm.bytecode",
                "evm.deployedBytecode",
                "evm.methodIdentifiers",
                "metadata"
              ],
              "": [
                "ast"
              ]
            }
          }
        }
      },
      "imports": [],
      "versionPragmas": [
        "0.8.24"
      ],
      "artifacts": [
        "VoteDapp"
      ]
    }
  }
}
